MANIFEST.in
README.md
setup.cfg
setup.py
aide_design/__init__.py
aide_design/cdc_functions.py
aide_design/constants.py
aide_design/expert_inputs.py
aide_design/floc_model.py
aide_design/init.py
aide_design/k_value_of_reductions_utility.py
aide_design/materials_database.py
aide_design/optional_inputs.py
aide_design/physchem.py
aide_design/pipedatabase.py
aide_design/pipeline_utility.py
aide_design/play.py
aide_design/units.py
aide_design/utility.py
aide_design.egg-info/PKG-INFO
aide_design.egg-info/SOURCES.txt
aide_design.egg-info/dependency_links.txt
aide_design.egg-info/not-zip-safe
aide_design.egg-info/requires.txt
aide_design.egg-info/top_level.txt
aide_design/data/pipedatabase.csv
aide_design/data/unit_definitions.txt
aide_design/strings/__init__.py
aide_design/strings/aide_constants.py
aide_design/strings/exceptions.py
aide_design/unit_process_design/StaRS.py
aide_design/unit_process_design/__init__.py
aide_design/unit_process_design/cdc.py
aide_design/unit_process_design/ent_tank.py
aide_design/unit_process_design/floc.py
aide_design/unit_process_design/lfom.py
tests/__init__.py
tests/test_k_value_of_reductions_utility.py
tests/test_lfom.py
tests/test_physchem.py
tests/test_pipedatabase.py
tests/test_pipeline_utility.py