Metadata-Version: 1.0
Name: aide-design
Version: 0.0.11
Summary: AguaClara Infrastructure Design Engine
Home-page: https://github.com/AguaClara/aguaclara_design
Author: AguaClara at Cornell
Author-email: aguaclara@cornell.edu
License: MIT
Platform: UNKNOWN
